LICENSE
MANIFEST.in
README.rst
setup.py
./jokk/__init__.py
./jokk/_compat.py
./jokk/server.py
docs/Makefile
docs/make.bat
docs/build/.buildinfo
docs/build/genindex.html
docs/build/index.html
docs/build/objects.inv
docs/build/search.html
docs/build/searchindex.js
docs/build/_sources/index.txt
docs/build/_static/ajax-loader.gif
docs/build/_static/basic.css
docs/build/_static/comment-bright.png
docs/build/_static/comment-close.png
docs/build/_static/comment.png
docs/build/_static/doctools.js
docs/build/_static/down-pressed.png
docs/build/_static/down.png
docs/build/_static/file.png
docs/build/_static/flasky.css
docs/build/_static/jquery.js
docs/build/_static/minus.png
docs/build/_static/plus.png
docs/build/_static/pygments.css
docs/build/_static/searchtools.js
docs/build/_static/small_flask.css
docs/build/_static/underscore.js
docs/build/_static/up-pressed.png
docs/build/_static/up.png
docs/build/_static/websupport.js
docs/build/doctrees/environment.pickle
docs/build/doctrees/index.doctree
docs/build/html/.buildinfo
docs/build/html/genindex.html
docs/build/html/index.html
docs/build/html/objects.inv
docs/build/html/search.html
docs/build/html/searchindex.js
docs/build/html/_sources/index.txt
docs/build/html/_static/ajax-loader.gif
docs/build/html/_static/basic.css
docs/build/html/_static/comment-bright.png
docs/build/html/_static/comment-close.png
docs/build/html/_static/comment.png
docs/build/html/_static/doctools.js
docs/build/html/_static/down-pressed.png
docs/build/html/_static/down.png
docs/build/html/_static/file.png
docs/build/html/_static/flasky.css
docs/build/html/_static/jquery.js
docs/build/html/_static/minus.png
docs/build/html/_static/plus.png
docs/build/html/_static/pygments.css
docs/build/html/_static/searchtools.js
docs/build/html/_static/small_flask.css
docs/build/html/_static/underscore.js
docs/build/html/_static/up-pressed.png
docs/build/html/_static/up.png
docs/build/html/_static/websupport.js
docs/source/conf.py
docs/source/index.rst
jokk.egg-info/PKG-INFO
jokk.egg-info/SOURCES.txt
jokk.egg-info/dependency_links.txt
jokk.egg-info/entry_points.txt
jokk.egg-info/requires.txt
jokk.egg-info/top_level.txt