Metadata-Version: 1.1
Name: jokk
Version: 0.2
Summary: RESTful Mock api server
Home-page: http://github.com/heavenshell/py-jokk
Author: Shinya Ohyanagi
Author-email: sohyanagi@gmail.com
License: BSD
Platform: any
Classifier: Development Status :: 4 - Beta
Classifier: Environment :: Web Environment
Classifier: Intended Audience :: Developers
Classifier: License :: OSI Approved :: BSD License
Classifier: Operating System :: OS Independent
Classifier: Programming Language :: Python
Classifier: Topic :: Internet :: WWW/HTTP
